.gitignore
.readthedocs.yml
README.rst
READMEkk.md
license.txt
requirements.txt
setup.cfg
setup.py
Log/fundamental_download.txt
Log/price_history_download.txt
docs/Makefile
docs/conf.py
docs/index.rst
docs/installation.rst
docs/make.bat
docs/_build/.buildinfo
docs/_build/genindex.html
docs/_build/index.html
docs/_build/objects.inv
docs/_build/search.html
docs/_build/searchindex.js
docs/_build/.doctrees/environment.pickle
docs/_build/.doctrees/index.doctree
docs/_build/_sources/index.rst.txt
docs/_build/_static/alabaster.css
docs/_build/_static/basic.css
docs/_build/_static/custom.css
docs/_build/_static/doctools.js
docs/_build/_static/documentation_options.js
docs/_build/_static/file.png
docs/_build/_static/jquery-3.5.1.js
docs/_build/_static/jquery.js
docs/_build/_static/language_data.js
docs/_build/_static/minus.png
docs/_build/_static/plus.png
docs/_build/_static/pygments.css
docs/_build/_static/searchtools.js
docs/_build/_static/underscore-1.3.1.js
docs/_build/_static/underscore.js
notebooks/Characterising companies based on financial metrics - Factor Analysis.ipynb
notebooks/Characterising companies based on financial metrics during covid19.ipynb
notebooks/Expanded Momentum Model.ipynb
notebooks/Momentum Model.ipynb
notebooks/sp500_metadata_fundamental.h5ad
notebooks/workingdesk.ipynb
notebooks/.ipynb_checkpoints/Characterising companies based on financial metrics - Factor Analysis-checkpoint.ipynb
notebooks/.ipynb_checkpoints/Characterising companies based on financial metrics during covid19-checkpoint.ipynb
notebooks/Combine_Signals_for_Enhanced_Alpha/project_7_starter.ipynb
notebooks/Combine_Signals_for_Enhanced_Alpha/project_helper.py
notebooks/Combine_Signals_for_Enhanced_Alpha/project_tests.py
notebooks/Combine_Signals_for_Enhanced_Alpha/requirements.txt
notebooks/Combine_Signals_for_Enhanced_Alpha/tests.py
notebooks/Combine_Signals_for_Enhanced_Alpha/.ipynb_checkpoints/project_7_starter-checkpoint.ipynb
quanp.egg-info/PKG-INFO
quanp.egg-info/SOURCES.txt
quanp.egg-info/dependency_links.txt
quanp.egg-info/entry_points.txt
quanp.egg-info/not-zip-safe
quanp.egg-info/requires.txt
quanp.egg-info/top_level.txt
