Metadata-Version: 2.1
Name: quanp
Version: 0.1.8
Summary: Quantitative Analysis in Python.
Home-page: http://github.com/hongkailee/quanp
Author: leehongkai@gmail.com
Author-email: leehongkai@gmail.com
License: BSD
Platform: UNKNOWN
Classifier: Development Status :: 5 - Production/Stable
Classifier: Environment :: Console
Classifier: Framework :: Jupyter
Classifier: Intended Audience :: Developers
Classifier: Natural Language :: English
Classifier: Operating System :: MacOS :: MacOS X
Classifier: Operating System :: Microsoft :: Windows
Classifier: Operating System :: POSIX :: Linux
Classifier: Programming Language :: Python :: 3
Classifier: Programming Language :: Python :: 3.6
Classifier: Topic :: Scientific/Engineering :: Visualization
Requires-Python: >=3.6
Provides-Extra: louvain
Provides-Extra: leiden
Provides-Extra: bbknn
Provides-Extra: scvi
Provides-Extra: rapids
Provides-Extra: magic
Provides-Extra: skmisc
Provides-Extra: harmony
Provides-Extra: doc
Provides-Extra: test
